argstart/__init__.py
argstart/main.py
argstart-0.0.3.dist-info/LICENSE
argstart-0.0.3.dist-info/METADATA
argstart-0.0.3.dist-info/WHEEL
argstart-0.0.3.dist-info/top_level.txt
argstart-0.0.3.dist-info/RECORD
