Metadata-Version: 2.1
Name: argstart
Version: 0.0.3
Summary: Run a "main" function automatically with the function's parameters as command-line arguments
Author: 731031
Author-email: 731031@gmail.com
Classifier: Programming Language :: Python :: 3
Classifier: License :: OSI Approved :: MIT License
Classifier: Operating System :: OS Independent
Requires-Python: >=3.6
License-File: LICENSE
Requires-Dist: docstring-parser
